jose-stubs/METADATA.toml
jose-stubs/__init__.pyi
jose-stubs/constants.pyi
jose-stubs/exceptions.pyi
jose-stubs/jwe.pyi
jose-stubs/jwk.pyi
jose-stubs/jws.pyi
jose-stubs/jwt.pyi
jose-stubs/py.typed
jose-stubs/utils.pyi
jose-stubs/backends/__init__.pyi
jose-stubs/backends/_asn1.pyi
jose-stubs/backends/base.pyi
jose-stubs/backends/cryptography_backend.pyi
jose-stubs/backends/ecdsa_backend.pyi
jose-stubs/backends/native.pyi
jose-stubs/backends/rsa_backend.pyi
types_python_jose-3.4.0.20250516.dist-info/licenses/LICENSE
types_python_jose-3.4.0.20250516.dist-info/METADATA
types_python_jose-3.4.0.20250516.dist-info/WHEEL
types_python_jose-3.4.0.20250516.dist-info/top_level.txt
types_python_jose-3.4.0.20250516.dist-info/RECORD
